blackboxai/__init__.py
blackboxai/chat.py
blackboxai/interpreter/__init__.py
blackboxai/interpreter/core/ARCHIVE_extend_system_message.py
blackboxai/interpreter/core/__init__.py
blackboxai/interpreter/core/browser.py
blackboxai/interpreter/core/core.py
blackboxai/interpreter/core/default_system_message.py
blackboxai/interpreter/core/render_message.py
blackboxai/interpreter/core/respond.py
blackboxai/interpreter/core/search.py
blackboxai/interpreter/core/server.py
blackboxai/interpreter/core/ARCHIVE_rag/ARCHIVE_get_relevant_procedures_string.py
blackboxai/interpreter/core/ARCHIVE_rag/ARCHIVE_local_get_relevant_procedures_string.py
blackboxai/interpreter/core/ARCHIVE_rag/__init__.py
blackboxai/interpreter/core/computer/__init__.py
blackboxai/interpreter/core/computer/computer.py
blackboxai/interpreter/core/computer/ai/__init__.py
blackboxai/interpreter/core/computer/ai/ai.py
blackboxai/interpreter/core/computer/browser/__init__.py
blackboxai/interpreter/core/computer/browser/browser.py
blackboxai/interpreter/core/computer/calendar/__init__.py
blackboxai/interpreter/core/computer/calendar/calendar.py
blackboxai/interpreter/core/computer/clipboard/__init__.py
blackboxai/interpreter/core/computer/clipboard/clipboard.py
blackboxai/interpreter/core/computer/contacts/__init__.py
blackboxai/interpreter/core/computer/contacts/contacts.py
blackboxai/interpreter/core/computer/display/__init__.py
blackboxai/interpreter/core/computer/display/display.py
blackboxai/interpreter/core/computer/docs/__init__.py
blackboxai/interpreter/core/computer/docs/docs.py
blackboxai/interpreter/core/computer/files/__init__.py
blackboxai/interpreter/core/computer/files/files.py
blackboxai/interpreter/core/computer/keyboard/__init__.py
blackboxai/interpreter/core/computer/keyboard/keyboard.py
blackboxai/interpreter/core/computer/mail/__init__.py
blackboxai/interpreter/core/computer/mail/mail.py
blackboxai/interpreter/core/computer/mouse/__init__.py
blackboxai-3.2.dist-info/LICENSE
blackboxai-3.2.dist-info/METADATA
blackboxai-3.2.dist-info/WHEEL
blackboxai-3.2.dist-info/entry_points.txt
blackboxai-3.2.dist-info/top_level.txt
blackboxai-3.2.dist-info/RECORD
