Metadata-Version: 2.1
Name: blackboxai
Version: 3.2
License-File: LICENSE
